codebundler/__init__.py
codebundler/__main__.py
codebundler/cli/__init__.py
codebundler/cli/commands.py
codebundler/core/__init__.py
codebundler/core/combiner.py
codebundler/core/filters.py
codebundler/core/transformers.py
codebundler/tui/__init__.py
codebundler/tui/app.py
codebundler/tui/bundler.py
codebundler/tui/widgets/__init__.py
codebundler/tui/widgets/directory_tree.py
codebundler/utils/__init__.py
codebundler/utils/helpers.py
codebundler/utils/watcher.py
codebundler-0.1.2.dist-info/licenses/LICENSE
codebundler-0.1.2.dist-info/METADATA
codebundler-0.1.2.dist-info/WHEEL
codebundler-0.1.2.dist-info/entry_points.txt
codebundler-0.1.2.dist-info/top_level.txt
codebundler-0.1.2.dist-info/RECORD
