Metadata-Version: 2.4
Name: codebundler
Version: 0.1.2
Summary: TUI application to combine and transform source code files for LLM usage
Author: Ben Moore
License: MIT
Project-URL: Homepage, https://github.com/mooresm/codebundler
Project-URL: Bug Tracker, https://github.com/mooresm/codebundler/issues
Keywords: code,source code,llm,combine,transform
Classifier: Development Status :: 3 - Alpha
Classifier: Environment :: Console
Classifier: Intended Audience :: Developers
Classifier: License :: OSI Approved :: MIT License
Classifier: Programming Language :: Python :: 3
Classifier: Programming Language :: Python :: 3.8
Classifier: Programming Language :: Python :: 3.9
Classifier: Programming Language :: Python :: 3.10
Classifier: Programming Language :: Python :: 3.11
Classifier: Topic :: Software Development :: Libraries :: Python Modules
Classifier: Topic :: Utilities
Requires-Python: >=3.8
License-File: LICENSE
Requires-Dist: rich>=10.0.0
Requires-Dist: watchdog>=2.1.0
Requires-Dist: textual<4.0.0,>=0.30.0
Requires-Dist: pyperclip>=1.8.0
Provides-Extra: dev
Requires-Dist: pytest; extra == "dev"
Requires-Dist: pytest-cov; extra == "dev"
Requires-Dist: black; extra == "dev"
Requires-Dist: flake8; extra == "dev"
Requires-Dist: isort; extra == "dev"
Dynamic: license-file
